bassa_reg/__init__.py
bassa_reg/bassa.py
bassa_reg/regression/numba_reg.py
bassa_reg/spike_and_slab/bassa_survival.py
bassa_reg/spike_and_slab/spike_and_slab.py
bassa_reg/spike_and_slab/spike_and_slab_core.py
bassa_reg/spike_and_slab/spike_and_slab_util_models.py
bassa_reg/spike_and_slab/utils/bassa_enums.py
bassa_reg/spike_and_slab/utils/can_use_latex.py
bassa_reg/spike_and_slab/utils/chain_visualization.py
bassa_reg/spike_and_slab/utils/feature_stats.py
bassa_reg/spike_and_slab/utils/gewekes_plot.py
bassa_reg/spike_and_slab/utils/latex_featname.py
bassa_reg/spike_and_slab/utils/sorted_s_model.py
bassa_reg/spike_and_slab/utils/upsert_plot.py
bassa_reg/spike_and_slab/utils/util_functions.py
bassa_reg-0.1.7.dist-info/licenses/LICENSE
expreiments/case_study_1/model_exploration.py
expreiments/case_study_1/prediction_pipeline.py
expreiments/case_study_2/model_exploration.py
expreiments/case_study_3/model_exploration.py
expreiments/synthetic_data/run.py
expreiments/utils/forward_regression.py
expreiments/utils/lasso_regression.py
expreiments/utils/utils.py
bassa_reg-0.1.7.dist-info/METADATA
bassa_reg-0.1.7.dist-info/WHEEL
bassa_reg-0.1.7.dist-info/top_level.txt
bassa_reg-0.1.7.dist-info/RECORD
